odoo/addons/portal_odoo_debranding/README.rst
odoo/addons/portal_odoo_debranding/__init__.py
odoo/addons/portal_odoo_debranding/__manifest__.py
odoo/addons/portal_odoo_debranding/i18n/portal_odoo_debranding.pot
odoo/addons/portal_odoo_debranding/readme/CONTRIBUTORS.rst
odoo/addons/portal_odoo_debranding/readme/DESCRIPTION.rst
odoo/addons/portal_odoo_debranding/static/description/icon.png
odoo/addons/portal_odoo_debranding/static/description/index.html
odoo/addons/portal_odoo_debranding/views/portal_templates.xml
odoo13_addon_portal_odoo_debranding-13.0.1.0.1.dev3.dist-info/METADATA
odoo13_addon_portal_odoo_debranding-13.0.1.0.1.dev3.dist-info/WHEEL
odoo13_addon_portal_odoo_debranding-13.0.1.0.1.dev3.dist-info/top_level.txt
odoo13_addon_portal_odoo_debranding-13.0.1.0.1.dev3.dist-info/RECORD
